make_selection/__init__.py
make_selection/make_selection.py
make_selection-1.0.7.dist-info/licenses/LICENSE
make_selection-1.0.7.dist-info/METADATA
make_selection-1.0.7.dist-info/WHEEL
make_selection-1.0.7.dist-info/top_level.txt
make_selection-1.0.7.dist-info/RECORD
