Metadata-Version: 2.4
Name: make_selection
Version: 1.0.7
Summary: Package for interactive command line menu
Author-email: Steven Frazee <stevefrazee123@gmail.com>
Classifier: License :: OSI Approved :: MIT License
Classifier: Development Status :: 4 - Beta
Classifier: Programming Language :: Python :: 3.9
Classifier: Operating System :: Microsoft :: Windows
Requires-Python: >=3.9
License-File: LICENSE
Dynamic: license-file
